numPrimos/__init__.py
numPrimos-1.0.dist-info/LICENSE
numPrimos-1.0.dist-info/METADATA
numPrimos-1.0.dist-info/WHEEL
numPrimos-1.0.dist-info/top_level.txt
numPrimos-1.0.dist-info/RECORD
